opennms_client
