Metadata-Version: 1.1
Name: opennms-client
Version: 0.2.3
Summary: A simple package to manage openNMS.
Home-page: https://github.com/mvillarejo/opennms_client
Author: Manuel Villarejo
Author-email: mjvillarejo@gmail.com
License: MIT License
Download-URL: https://github.com/mvillarejo/opennms_client/releases
Keywords: opennms_client opennms client python
Platform: any
Classifier: Development Status :: 4 - Beta
Classifier: Environment :: Console
Classifier: Intended Audience :: Developers
Classifier: Natural Language :: English
Classifier: Intended Audience :: Information Technology
Classifier: License :: OSI Approved :: MIT License
Classifier: Operating System :: OS Independent
Classifier: Programming Language :: Python :: Implementation :: PyPy
Classifier: Topic :: Software Development :: Libraries :: Python Modules
